setup.py
cipher_crns/__init__.py
cipher_crns/affinecipher.py
cipher_crns/caesarcipher.py
cipher_crns/hillcipher.py
cipher_crns/playfair.py
cipher_crns.egg-info/PKG-INFO
cipher_crns.egg-info/SOURCES.txt
cipher_crns.egg-info/dependency_links.txt
cipher_crns.egg-info/requires.txt
cipher_crns.egg-info/top_level.txt