Metadata-Version: 1.0
Name: cipher-crns
Version: 0.3
Summary: Ciphers
Home-page: UNKNOWN
Author: Nirav Shah
Author-email: 15ce128@charusat.edu.in
License: MIT
Platform: UNKNOWN
